grongier/__init__.py
grongier/cls/Grongier/PEX/BusinessOperation.cls
grongier/cls/Grongier/PEX/BusinessProcess.cls
grongier/cls/Grongier/PEX/BusinessService.cls
grongier/cls/Grongier/PEX/Common.cls
grongier/cls/Grongier/PEX/Director.cls
grongier/cls/Grongier/PEX/InboundAdapter.cls
grongier/cls/Grongier/PEX/Message.cls
grongier/cls/Grongier/PEX/OutboundAdapter.cls
grongier/cls/Grongier/PEX/PickleMessage.cls
grongier/cls/Grongier/PEX/Test.cls
grongier/cls/Grongier/PEX/Utils.cls
grongier/cls/Grongier/PEX/Duplex/Operation.cls
grongier/cls/Grongier/PEX/Duplex/Process.cls
grongier/cls/Grongier/PEX/Duplex/Service.cls
grongier/cls/Grongier/PEX/PrivateSession/Duplex.cls
grongier/cls/Grongier/PEX/PrivateSession/Message/Ack.cls
grongier/cls/Grongier/PEX/PrivateSession/Message/Poll.cls
grongier/cls/Grongier/PEX/PrivateSession/Message/Start.cls
grongier/cls/Grongier/PEX/PrivateSession/Message/Stop.cls
grongier/cls/Grongier/Service/WSGI.cls
grongier/pex/__init__.py
grongier/pex/__main__.py
grongier/pex/_business_host.py
grongier/pex/_cli.py
grongier/pex/_common.py
grongier/pex/_director.py
grongier/pex/_utils.py
grongier/pex/wsgi/handlers.py
iop/__init__.py
iop/__main__.py
iop/_async_request.py
iop/_business_host.py
iop/_business_operation.py
iop/_business_process.py
iop/_business_service.py
iop/_cli.py
iop/_common.py
iop/_debugpy.py
iop/_decorators.py
iop/_director.py
iop/_dispatch.py
iop/_generator_request.py
iop/_inbound_adapter.py
iop/_iris.py
iop/_log_manager.py
iop/_message.py
iop/_message_validator.py
iop/_outbound_adapter.py
iop/_private_session_duplex.py
iop/_private_session_process.py
iop/_remote.py
iop/_serialization.py
iop/_utils.py
iop/cls/IOP/BusinessOperation.cls
iop/cls/IOP/BusinessProcess.cls
iop/cls/IOP/BusinessService.cls
iop/cls/IOP/Common.cls
iop/cls/IOP/Director.cls
iop/cls/IOP/InboundAdapter.cls
iop/cls/IOP/Message.cls
iop/cls/IOP/OutboundAdapter.cls
iop/cls/IOP/PickleMessage.cls
iop/cls/IOP/Projection.cls
iop/cls/IOP/Test.cls
iop/cls/IOP/Utils.cls
iris_pex_embedded_python-3.5.3.dist-info/licenses/LICENSE
iris_pex_embedded_python-3.5.3.dist-info/METADATA
iris_pex_embedded_python-3.5.3.dist-info/WHEEL
iris_pex_embedded_python-3.5.3.dist-info/entry_points.txt
iris_pex_embedded_python-3.5.3.dist-info/top_level.txt
iris_pex_embedded_python-3.5.3.dist-info/RECORD
