Metadata-Version: 2.4
Name: iris_pex_embedded_python
Version: 3.5.3
Summary: Iris Interoperability based on Embedded Python
Author-email: grongier <guillaume.rongier@intersystems.com>
License: MIT License
Project-URL: homepage, https://github.com/grongierisc/interoperability-embedded-python
Project-URL: documentation, https://github.com/grongierisc/interoperability-embedded-python/blob/master/README.md
Project-URL: repository, https://github.com/grongierisc/interoperability-embedded-python
Project-URL: issues, https://github.com/grongierisc/interoperability-embedded-python/issues
Keywords: iris,intersystems,python,embedded
Classifier: Development Status :: 5 - Production/Stable
Classifier: Intended Audience :: Developers
Classifier: License :: OSI Approved :: MIT License
Classifier: Operating System :: OS Independent
Classifier: Programming Language :: Python :: 3.6
Classifier: Programming Language :: Python :: 3.7
Classifier: Programming Language :: Python :: 3.8
Classifier: Programming Language :: Python :: 3.9
Classifier: Programming Language :: Python :: 3.10
Classifier: Programming Language :: Python :: 3.11
Classifier: Programming Language :: Python :: 3.12
Classifier: Topic :: Utilities
License-File: LICENSE
Requires-Dist: pydantic>=2.0.0
Requires-Dist: xmltodict>=0.12.0
Requires-Dist: iris-embedded-python-wrapper>=0.0.6
Requires-Dist: jsonpath-ng>=1.7.0
Requires-Dist: debugpy>=1.8.0
Requires-Dist: requests>=2.24.0
Dynamic: license-file
